jupyterlab_algorithm_style_extension/__init__.py
jupyterlab_algorithm_style_extension/_version.py
jupyterlab_algorithm_style_extension-0.1.1.data/data/share/jupyter/labextensions/jupyterlab-algorithm-style-extension/build_log.json
jupyterlab_algorithm_style_extension-0.1.1.data/data/share/jupyter/labextensions/jupyterlab-algorithm-style-extension/package.json
jupyterlab_algorithm_style_extension-0.1.1.data/data/share/jupyter/labextensions/jupyterlab-algorithm-style-extension/static/lib_index_js.e30dbf3876ec59e3afc6.js
jupyterlab_algorithm_style_extension-0.1.1.data/data/share/jupyter/labextensions/jupyterlab-algorithm-style-extension/static/lib_index_js.e30dbf3876ec59e3afc6.js.map
jupyterlab_algorithm_style_extension-0.1.1.data/data/share/jupyter/labextensions/jupyterlab-algorithm-style-extension/static/remoteEntry.176967f5b57eb5a16d6c.js
jupyterlab_algorithm_style_extension-0.1.1.data/data/share/jupyter/labextensions/jupyterlab-algorithm-style-extension/static/remoteEntry.176967f5b57eb5a16d6c.js.map
jupyterlab_algorithm_style_extension-0.1.1.data/data/share/jupyter/labextensions/jupyterlab-algorithm-style-extension/static/style.js
jupyterlab_algorithm_style_extension-0.1.1.data/data/share/jupyter/labextensions/jupyterlab-algorithm-style-extension/static/style_index_js.a766801e3528271eac9e.js
jupyterlab_algorithm_style_extension-0.1.1.data/data/share/jupyter/labextensions/jupyterlab-algorithm-style-extension/static/style_index_js.a766801e3528271eac9e.js.map
jupyterlab_algorithm_style_extension-0.1.1.data/data/share/jupyter/labextensions/jupyterlab-algorithm-style-extension/install.json
jupyterlab_algorithm_style_extension-0.1.1.dist-info/METADATA
jupyterlab_algorithm_style_extension-0.1.1.dist-info/WHEEL
jupyterlab_algorithm_style_extension-0.1.1.dist-info/licenses/LICENSE
jupyterlab_algorithm_style_extension-0.1.1.dist-info/RECORD
