Metadata-Version: 2.1
Name: jupyterlab_algorithm_style_extension
Version: 0.1.1
Summary: jupyterlab-algorithm-style-extension
Project-URL: Homepage, https://github.com/KrunkZhou/jupyterlab-algorithm-style-extension
Project-URL: Bug Tracker, https://github.com/KrunkZhou/jupyterlab-algorithm-style-extension/issues
Project-URL: Repository, https://github.com/KrunkZhou/jupyterlab-algorithm-style-extension.git
Author-email: Tianyu Zhou <zhout34@mcmaster.ca>
License: BSD 3-Clause License
License-File: LICENSE
Classifier: Framework :: Jupyter
Classifier: Framework :: Jupyter :: JupyterLab
Classifier: Framework :: Jupyter :: JupyterLab :: 4
Classifier: Framework :: Jupyter :: JupyterLab :: Extensions
Classifier: Framework :: Jupyter :: JupyterLab :: Extensions :: Prebuilt
Classifier: License :: OSI Approved :: BSD License
Classifier: Programming Language :: Python
Classifier: Programming Language :: Python :: 3
Classifier: Programming Language :: Python :: 3.8
Classifier: Programming Language :: Python :: 3.9
Classifier: Programming Language :: Python :: 3.10
Classifier: Programming Language :: Python :: 3.11
Classifier: Programming Language :: Python :: 3.12
Requires-Python: >=3.8
